{
  "updated": "2026-07-24T08:30:15.719535Z",
  "stocks": [
    {
      "ticker": "MU",
      "name": "美光 Micron",
      "currency": "USD",
      "price": 990.21,
      "change": 3.2,
      "revenue": 37378000000.0,
      "gross_margin": 39.8,
      "eps": 45.65,
      "pe": 21.691347
    },
    {
      "ticker": "005930.KS",
      "name": "三星电子",
      "currency": "KRW",
      "price": 249500.0,
      "change": -7.59,
      "revenue": 333605938000000.0,
      "gross_margin": 39.4,
      "eps": null,
      "pe": null
    },
    {
      "ticker": "000660.KS",
      "name": "SK海力士",
      "currency": "KRW",
      "price": 1759000.0,
      "change": -8.34,
      "revenue": 97146675000000.0,
      "gross_margin": 60.4,
      "eps": null,
      "pe": null
    },
    {
      "ticker": "300223.SZ",
      "name": "君正集成",
      "currency": "CNY",
      "price": 143.65,
      "change": -5.34,
      "revenue": 4741007597.96,
      "gross_margin": 34.1,
      "eps": 1.29,
      "pe": 111.35659
    }
  ],
  "dcf": {
    "ok": true,
    "fcf0_b": 1.67,
    "flows_b": [
      1.87,
      2.09,
      2.34,
      2.62,
      2.94
    ],
    "tv_b": 43.25,
    "ev_b": 35.66,
    "fair_value": 55309362608.83,
    "price": 990.21,
    "upside": 5585619375.55,
    "assumptions": {
      "growth_5y": 0.12,
      "terminal_growth": 0.03,
      "wacc": 0.1
    }
  },
  "micron": [],
  "hbm": [
    {
      "title": "AMD Instinct MI400 Series and Helios Rack Debut: CDNA 5 Goes 2 nm, Plus ROCm.ai and \"Gorgon Halo\"",
      "link": "https://www.techpowerup.com/351006/amd-instinct-mi400-series-and-helios-rack-debut-cdna-5-goes-2-nm-plus-rocm-ai-and-gorgon-halo",
      "src": "TechPowerUp",
      "date": "2026-07-23T19:30:30",
      "zh": "AMD Instinct MI400 系列和 Helios 机架首次亮相：CDNA 5 采用 2 nm，加上 ROCm.ai 和“Gorgon Halo”"
    }
  ]
}